setup.py
cloudyqueue/__init__.py
cloudyqueue/common.py
cloudyqueue/queue.py
cloudyqueue.egg-info/PKG-INFO
cloudyqueue.egg-info/SOURCES.txt
cloudyqueue.egg-info/dependency_links.txt
cloudyqueue.egg-info/requires.txt
cloudyqueue.egg-info/top_level.txt
cloudyqueue.egg-info/zip-safe