Metadata-Version: 1.0
Name: cloudyqueue
Version: 0.0.0
Summary: Dictionary interface to cloud providers.
Home-page: https://github.com/wnyc/cloudyqueue 
Author: Adam DePrince
Author-email: adeprince@nypublicradio.org
License: GPL
Platform: UNKNOWN
